{"inkVersion":20,"root":[[{"->":"intro"},["done",{"#f":5,"#n":"g-0"}],null],"done",{"intro":[["^Mrcalindas?Smiling \"Hi ","ev",{"VAR?":"player_name"},"out","/ev","^! How are you doing?\"","\n",["ev",{"^->":"intro.0.7.$r1"},{"temp=":"$r"},"str",{"->":".^.s"},[{"#n":"$r1"}],"/str","/ev",{"*":".^.^.c-0","flg":18},{"s":["^I'm doing well, Mr. Calindas. Here for a quick chat if possible. How are you?",{"->":"$r","var":true},null]}],["ev",{"^->":"intro.0.8.$r1"},{"temp=":"$r"},"str",{"->":".^.s"},[{"#n":"$r1"}],"/str","/ev",{"*":".^.^.c-1","flg":18},{"s":["^Okay! I have a few questions, but how are you?",{"->":"$r","var":true},null]}],{"c-0":["ev",{"^->":"intro.0.c-0.$r2"},"/ev",{"temp=":"$r"},{"->":".^.^.7.s"},[{"#n":"$r2"}],"\n",{"->":"Chat1"},{"#f":5}],"c-1":["ev",{"^->":"intro.0.c-1.$r2"},"/ev",{"temp=":"$r"},{"->":".^.^.8.s"},[{"#n":"$r2"}],"\n",{"->":"Chat1"},{"#f":5}]}],{"#f":1}],"Chat1":[["^Mrcalindas?Smiling \"Not bad at all. What can I help you with?\"","\n",["ev",{"^->":"Chat1.0.2.$r1"},{"temp=":"$r"},"str",{"->":".^.s"},[{"#n":"$r1"}],"/str","/ev",{"*":".^.^.c-0","flg":18},{"s":["^I have a friend who doesn't have a much access to her family's health history, and she doesn't know where to turn for more information.",{"->":"$r","var":true},null]}],["ev",{"^->":"Chat1.0.3.$r1"},{"temp=":"$r"},"str",{"->":".^.s"},[{"#n":"$r1"}],"/str","/ev",{"*":".^.^.c-1","flg":18},{"s":["^Do you have any resources for people who don't know their parental health history?",{"->":"$r","var":true},null]}],{"c-0":["ev",{"^->":"Chat1.0.c-0.$r2"},"/ev",{"temp=":"$r"},{"->":".^.^.2.s"},[{"#n":"$r2"}],"\n",{"->":"Explain1"},{"#f":5}],"c-1":["ev",{"^->":"Chat1.0.c-1.$r2"},"/ev",{"temp=":"$r"},{"->":".^.^.3.s"},[{"#n":"$r2"}],"\n",{"->":"Explain1"},{"#f":5}]}],{"#f":1}],"Explain1":[["^Mrcalindas?Neutral \"Oh! Yes, there are a few options.\"","\n",["ev",{"^->":"Explain1.0.2.$r1"},{"temp=":"$r"},"str",{"->":".^.s"},[{"#n":"$r1"}],"/str","/ev",{"*":".^.^.c-0","flg":18},{"s":["^She technically does have access to her mom if that helps at all.",{"->":"$r","var":true},null]}],["ev",{"^->":"Explain1.0.3.$r1"},{"temp=":"$r"},"str",{"->":".^.s"},[{"#n":"$r1"}],"/str","/ev",{"*":".^.^.c-1","flg":18},{"s":["^She really wants to be aware of anything she should be watching out for.",{"->":"$r","var":true},null]}],{"c-0":["ev",{"^->":"Explain1.0.c-0.$r2"},"/ev",{"temp=":"$r"},{"->":".^.^.2.s"},[{"#n":"$r2"}],"\n",{"->":"Suggestion1"},{"#f":5}],"c-1":["ev",{"^->":"Explain1.0.c-1.$r2"},"/ev",{"temp=":"$r"},{"->":".^.^.3.s"},[{"#n":"$r2"}],"\n",{"->":"Suggestion2"},{"#f":5}]}],{"#f":1}],"Suggestion1":[["^Mrcalindas?Smiling \"I definitely think if she can, she should talk to her mom.\"","\n","^Mrcalindas?Smiling \"She will likely also be able to tell her some possible information about her father if she has it, and about her grandparents.\"","\n","ev","str","^Mrcalindas_Day 2_Mr. Calindas suggests Lila prioritize contacting her mom to find her family health history","/str","/ev",{"VAR=":"notification","re":true},{"#":"notification"},["ev",{"^->":"Suggestion1.0.11.$r1"},{"temp=":"$r"},"str",{"->":".^.s"},[{"#n":"$r1"}],"/str","/ev",{"*":".^.^.c-0","flg":18},{"s":["^Her mom is pretty inaccessible right now traveling. Is there any other way she can look into her history herself?",{"->":"$r","var":true},null]}],["ev",{"^->":"Suggestion1.0.12.$r1"},{"temp=":"$r"},"str",{"->":".^.s"},[{"#n":"$r1"}],"/str","/ev",{"*":".^.^.c-1","flg":18},{"s":["^That would be great! I'll confirm with Lila and get back to you. ",{"->":"$r","var":true},null]}],{"c-0":["ev",{"^->":"Suggestion1.0.c-0.$r2"},"/ev",{"temp=":"$r"},{"->":".^.^.11.s"},[{"#n":"$r2"}],"\n",{"->":"Suggestion2"},{"#f":5}],"c-1":["ev",{"^->":"Suggestion1.0.c-1.$r2"},"/ev",{"temp=":"$r"},{"->":".^.^.12.s"},[{"#n":"$r2"}],"\n",{"->":"Goodbye"},{"#f":5}]}],{"#f":1}],"Suggestion2":[["^Mrcalindas?Smiling \"Yeah! Genetic testing is available to look for gene markers that can make individuals more at-risk for certain diseases, syndromes, and reactions.\"","\n","^Mrcalindas?Smiling \"There are other tests she should do to be safe if she doesn't have a lot of healthcare background, like comprehensive tests to check high-risk markers.\"","\n","ev","str","^Mrcalindas_Day 2_Mr. Calindas suggests Lila look into genetic testing on medlineplus.gov/genetics to find genetic markers that might indicate she is prone to certain illnesses, and also says that comprehensive testing is important if she doesn’t know what she should be looking out for_Lila2","/str","/ev",{"VAR=":"notification","re":true},{"#":"notification"},["ev",{"^->":"Suggestion2.0.11.$r1"},{"temp=":"$r"},"str",{"->":".^.s"},[{"#n":"$r1"}],"/str","/ev",{"*":".^.^.c-0","flg":18},{"s":["^Are there any other options?",{"->":"$r","var":true},null]}],["ev",{"^->":"Suggestion2.0.12.$r1"},{"temp=":"$r"},"str",{"->":".^.s"},[{"#n":"$r1"}],"/str","/ev",{"*":".^.^.c-1","flg":18},{"s":["^This is great information, could you send me any direct resources so I can pass them along to her?",{"->":"$r","var":true},null]}],{"c-0":["ev",{"^->":"Suggestion2.0.c-0.$r2"},"/ev",{"temp=":"$r"},{"->":".^.^.11.s"},[{"#n":"$r2"}],"\n",{"->":"Suggestion1"},{"#f":5}],"c-1":["ev",{"^->":"Suggestion2.0.c-1.$r2"},"/ev",{"temp=":"$r"},{"->":".^.^.12.s"},[{"#n":"$r2"}],"\n",{"->":"Goodbye"},{"#f":5}]}],{"#f":1}],"Goodbye":[["^Mrcalindas?Smiling \"Yeah, no problem!\"","\n",["ev",{"^->":"Goodbye.0.2.$r1"},{"temp=":"$r"},"str",{"->":".^.s"},[{"#n":"$r1"}],"/str","/ev",{"*":".^.^.c-0","flg":18},{"s":["^Thanks! See you around, Mr. Calindas!",{"->":"$r","var":true},null]}],["ev",{"^->":"Goodbye.0.3.$r1"},{"temp=":"$r"},"str",{"->":".^.s"},[{"#n":"$r1"}],"/str","/ev",{"*":".^.^.c-1","flg":18},{"s":["^Much appreciated, thank you! Bye!",{"->":"$r","var":true},null]}],{"c-0":["ev",{"^->":"Goodbye.0.c-0.$r2"},"/ev",{"temp=":"$r"},{"->":".^.^.2.s"},[{"#n":"$r2"}],"\n","end",{"#f":5}],"c-1":["ev",{"^->":"Goodbye.0.c-1.$r2"},"/ev",{"temp=":"$r"},{"->":".^.^.3.s"},[{"#n":"$r2"}],"\n","end",{"#f":5}]}],{"#f":1}],"global decl":["ev","str","^","/str",{"VAR=":"player_name"},"str","^","/str",{"VAR=":"notification"},"str","^","/str",{"VAR=":"new_contact"},"str","^","/str",{"VAR=":"new_quest"},"/ev","end",null],"#f":1}],"listDefs":{}}