{"inkVersion":20,"root":[[{"->":"intro"},["done",{"#f":5,"#n":"g-0"}],null],"done",{"intro":[["^Elisa?Smiling \"Hey ","ev",{"VAR?":"player_name"},"out","/ev","^.\"","\n",["ev",{"^->":"intro.0.7.$r1"},{"temp=":"$r"},"str",{"->":".^.s"},[{"#n":"$r1"}],"/str","/ev",{"*":".^.^.c-0","flg":18},{"s":["^What's up, Elisa?",{"->":"$r","var":true},null]}],["ev",{"^->":"intro.0.8.$r1"},{"temp=":"$r"},"str",{"->":".^.s"},[{"#n":"$r1"}],"/str","/ev",{"*":".^.^.c-1","flg":18},{"s":["^Are you studying, I see?",{"->":"$r","var":true},null]}],{"c-0":["ev",{"^->":"intro.0.c-0.$r2"},"/ev",{"temp=":"$r"},{"->":".^.^.7.s"},[{"#n":"$r2"}],"\n",{"->":"Chat1"},{"#f":5}],"c-1":["ev",{"^->":"intro.0.c-1.$r2"},"/ev",{"temp=":"$r"},{"->":".^.^.8.s"},[{"#n":"$r2"}],"\n",{"->":"Chat1"},{"#f":5}]}],{"#f":1}],"Chat1":[["^Elisa?Smiling \"My mom just sent a meme in the family group chat. I'm shocked. It was good!\"","\n",["ev",{"^->":"Chat1.0.2.$r1"},{"temp=":"$r"},"str",{"->":".^.s"},[{"#n":"$r1"}],"/str","/ev",{"*":".^.^.c-0","flg":18},{"s":["^That's so funny!",{"->":"$r","var":true},null]}],["ev",{"^->":"Chat1.0.3.$r1"},{"temp=":"$r"},"str",{"->":".^.s"},[{"#n":"$r1"}],"/str","/ev",{"*":".^.^.c-1","flg":18},{"s":["^Can I ask for your opinion on something?",{"->":"$r","var":true},null]}],{"c-0":["ev",{"^->":"Chat1.0.c-0.$r2"},"/ev",{"temp=":"$r"},{"->":".^.^.2.s"},[{"#n":"$r2"}],"\n",{"->":"Chat2"},{"#f":5}],"c-1":["ev",{"^->":"Chat1.0.c-1.$r2"},"/ev",{"temp=":"$r"},{"->":".^.^.3.s"},[{"#n":"$r2"}],"\n",{"->":"Explain1"},{"#f":5}]}],{"#f":1}],"Chat2":[["^Elisa?Smiling \"Now all my siblings are hopping on it... ugh this is so distracting actually. I should be studying...\"","\n",["ev",{"^->":"Chat2.0.2.$r1"},{"temp=":"$r"},"str",{"->":".^.s"},[{"#n":"$r1"}],"/str","/ev",{"*":".^.^.c-0","flg":18},{"s":["^Can I ask you something?",{"->":"$r","var":true},null]}],{"c-0":["ev",{"^->":"Chat2.0.c-0.$r2"},"/ev",{"temp=":"$r"},{"->":".^.^.2.s"},[{"#n":"$r2"}],"\n",{"->":"Explain1"},{"#f":5}]}],{"#f":1}],"Explain1":[["^Elisa?Neutral \"Yeah, sure you can ask me anything and I'll tell you if I'm comfortable answering.\"","\n",["ev",{"^->":"Explain1.0.2.$r1"},{"temp=":"$r"},"str",{"->":".^.s"},[{"#n":"$r1"}],"/str","/ev",{"*":".^.^.c-0","flg":18},{"s":["^Do you get nervous about going to the doctors?",{"->":"$r","var":true},null]}],{"c-0":["ev",{"^->":"Explain1.0.c-0.$r2"},"/ev",{"temp=":"$r"},{"->":".^.^.2.s"},[{"#n":"$r2"}],"\n",{"->":"Explain2"},{"#f":5}]}],{"#f":1}],"Explain2":[["^Elisa?Smiling \"I am totally fine talking about this. You scared me for a second! But, no, I don't get nervous at the doctor's. My parents are a different story though it's like an entire ordeal.\"","\n",["ev",{"^->":"Explain2.0.2.$r1"},{"temp=":"$r"},"str",{"->":".^.s"},[{"#n":"$r1"}],"/str","/ev",{"*":".^.^.c-0","flg":18},{"s":["^What do you mean?",{"->":"$r","var":true},null]}],["ev",{"^->":"Explain2.0.3.$r1"},{"temp=":"$r"},"str",{"->":".^.s"},[{"#n":"$r1"}],"/str","/ev",{"*":".^.^.c-1","flg":18},{"s":["^What kind of ordeal?",{"->":"$r","var":true},null]}],{"c-0":["ev",{"^->":"Explain2.0.c-0.$r2"},"/ev",{"temp=":"$r"},{"->":".^.^.2.s"},[{"#n":"$r2"}],"\n",{"->":"Suggestion1"},{"#f":5}],"c-1":["ev",{"^->":"Explain2.0.c-1.$r2"},"/ev",{"temp=":"$r"},{"->":".^.^.3.s"},[{"#n":"$r2"}],"\n",{"->":"Suggestion2"},{"#f":5}]}],{"#f":1}],"Suggestion1":[["ev","str","^Elisa_Day 3_Mrs. Lee can write down her questions or symptoms before her appointment_Mrslee3","/str","/ev",{"VAR=":"notification","re":true},{"#":"notification Elisa_Day 3_Mrs. Lee can write down her questions or symptoms before her appointment_Mrslee3"},"^Elisa?Smiling \"Actually it is a good idea, but they write down any questions or symptoms to bring up to the doctor.\"","\n",["ev",{"^->":"Suggestion1.0.9.$r1"},{"temp=":"$r"},"str",{"->":".^.s"},[{"#n":"$r1"}],"/str","/ev",{"*":".^.^.c-0","flg":18},{"s":["^That's smart, and so they just read it?",{"->":"$r","var":true},null]}],["ev",{"^->":"Suggestion1.0.10.$r1"},{"temp=":"$r"},"str",{"->":".^.s"},[{"#n":"$r1"}],"/str","/ev",{"*":".^.^.c-1","flg":18},{"s":["^That's a good idea.",{"->":"$r","var":true},null]}],{"c-0":["ev",{"^->":"Suggestion1.0.c-0.$r2"},"/ev",{"temp=":"$r"},{"->":".^.^.9.s"},[{"#n":"$r2"}],"\n",{"->":"Suggestion2"},{"#f":5}],"c-1":["ev",{"^->":"Suggestion1.0.c-1.$r2"},"/ev",{"temp=":"$r"},{"->":".^.^.10.s"},[{"#n":"$r2"}],"\n",{"->":"Goodbye"},{"#f":5}]}],{"#f":1}],"Suggestion2":[["ev","str","^Elisa_Day 3_Translators can sit in on the doctor's appointment (Spanish only)","/str","/ev",{"VAR=":"notification","re":true},{"#":"notification Elisa_Day 3_Translators can sit in on the doctor's appointment (Spanish only)"},"^Elisa?Smiling \"Yeah, my parents don't speak English as good as me so like when my dad goes he gets a spanish translator to come into the room with him.\"","\n","^Elisa?Smiling \"And they will translate any of his questions. I'm pretty sure it's only available for spanish at our clinic here.\"","\n",["ev",{"^->":"Suggestion2.0.11.$r1"},{"temp=":"$r"},"str",{"->":".^.s"},[{"#n":"$r1"}],"/str","/ev",{"*":".^.^.c-0","flg":18},{"s":["^That's a good resource though",{"->":"$r","var":true},null]}],["ev",{"^->":"Suggestion2.0.12.$r1"},{"temp=":"$r"},"str",{"->":".^.s"},[{"#n":"$r1"}],"/str","/ev",{"*":".^.^.c-1","flg":18},{"s":["^A translator! Awesome!",{"->":"$r","var":true},null]}],{"c-0":["ev",{"^->":"Suggestion2.0.c-0.$r2"},"/ev",{"temp=":"$r"},{"->":".^.^.11.s"},[{"#n":"$r2"}],"\n",{"->":"Suggestion1"},{"#f":5}],"c-1":["ev",{"^->":"Suggestion2.0.c-1.$r2"},"/ev",{"temp=":"$r"},{"->":".^.^.12.s"},[{"#n":"$r2"}],"\n",{"->":"Goodbye"},{"#f":5}]}],{"#f":1}],"Goodbye":[["^Elisa?Neutral \"Okay, enough talking about my parents, this conversation is making me sleepy.\"","\n",["ev",{"^->":"Goodbye.0.2.$r1"},{"temp=":"$r"},"str",{"->":".^.s"},[{"#n":"$r1"}],"/str","/ev",{"*":".^.^.c-0","flg":18},{"s":["^Haha always nice chatting, Elisa",{"->":"$r","var":true},null]}],["ev",{"^->":"Goodbye.0.3.$r1"},{"temp=":"$r"},"str",{"->":".^.s"},[{"#n":"$r1"}],"/str","/ev",{"*":".^.^.c-1","flg":18},{"s":["^Buh-bye!",{"->":"$r","var":true},null]}],{"c-0":["ev",{"^->":"Goodbye.0.c-0.$r2"},"/ev",{"temp=":"$r"},{"->":".^.^.2.s"},[{"#n":"$r2"}],"\n","end",{"#f":5}],"c-1":["ev",{"^->":"Goodbye.0.c-1.$r2"},"/ev",{"temp=":"$r"},{"->":".^.^.3.s"},[{"#n":"$r2"}],"\n","end",{"#f":5}]}],{"#f":1}],"global decl":["ev","str","^","/str",{"VAR=":"player_name"},"str","^","/str",{"VAR=":"notification"},"str","^","/str",{"VAR=":"new_contact"},"str","^","/str",{"VAR=":"new_quest"},"/ev","end",null],"#f":1}],"listDefs":{}}